pyexcuses/__init__.py
pyexcuses/exc.py
pyexcuses/excuses_en.py
pyexcuses/excuses_es.py
pyexcuses/pyexcuses.py
pyexcuses/solutions_en.py
pyexcuses/solutions_es.py
pyexcuses-0.0.2.dist-info/LICENSE
pyexcuses-0.0.2.dist-info/METADATA
pyexcuses-0.0.2.dist-info/WHEEL
pyexcuses-0.0.2.dist-info/top_level.txt
pyexcuses-0.0.2.dist-info/RECORD
