Metadata-Version: 2.1
Name: pyexcuses
Version: 0.0.2
Summary: Package to fix all your coding problems.
Author: Darren Zou, Peter D'Angelo, Gene Park, Joseph Chege
Author-email: Joseph Chege <jcm9824@nyu.edu>, Darren Zou <dz2218@nyu.edu>, Peter D'Angelo <pgd8870@nyu.edu>, Gene Park <ghp7469@nyu.edu>, Jack Zhang <yz6973@nyu.edu>
Project-URL: Homepage, https://github.com/software-students-fall2024/3-python-package-realoriginal
Project-URL: Issues, https://github.com/software-students-fall2024/3-python-package-realoriginal/issues
Classifier: Programming Language :: Python :: 3
Classifier: License :: OSI Approved :: GNU General Public License v3 (GPLv3)
Classifier: Operating System :: OS Independent
Requires-Python: >=3.10
License-File: LICENSE
Requires-Dist: typing
